autowriterllm/__init__.py
autowriterllm/ai_content_generator.py
autowriterllm/markdown_to_pdf_converter.py
AutoWriterLLM-0.1.0.dist-info/LICENSE
AutoWriterLLM-0.1.0.dist-info/METADATA
AutoWriterLLM-0.1.0.dist-info/WHEEL
AutoWriterLLM-0.1.0.dist-info/top_level.txt
AutoWriterLLM-0.1.0.dist-info/RECORD
